[
  {
    "id": "ersfjordbotn",
    "name": "Ersfjordbotn",
    "lat": 69.6626,
    "lon": 18.3738,
    "distanceKm": 25,
    "lightPollution": 1,
    "horizon": "north",
    "description": "Classic fjord aurora spot with mountains and reflections.",
    "busStop": "Ersfjordbotn skole",
    "parking": "Ersfjordbotn",
    "source": "Tromsø kommune"
  },
  {
    "id": "kattfjordvatnet",
    "name": "Kattfjordvatnet",
    "lat": 69.6667,
    "lon": 18.2,
    "distanceKm": 35,
    "lightPollution": 1,
    "horizon": "north",
    "description": "Large lake offering unobstructed sky views and aurora reflections."
  },
  {
    "id": "grotfjord",
    "name": "Grotfjord",
    "lat": 69.75,
    "lon": 18.2167,
    "distanceKm": 45,
    "lightPollution": 1,
    "horizon": "north",
    "description": "Dark fjord area north of Kvaloya with wide northern horizon."
  },
  {
    "id": "sommaroy",
    "name": "Sommarøy",
    "lat": 69.6353,
    "lon": 17.9927,
    "distanceKm": 55,
    "lightPollution": 1,
    "horizon": "northwest",
    "description": "Small island with extremely dark skies and ocean horizon."
  },
  {
    "id": "sandvika_beach",
    "name": "Sandvika Beach",
    "lat": 69.6439,
    "lon": 18.0061,
    "distanceKm": 55,
    "lightPollution": 1,
    "horizon": "northwest",
    "description": "Wide beach near Sommarøy with open sky views."
  },
  {
    "id": "skulsfjord",
    "name": "Skulsfjord",
    "lat": 69.728,
    "lon": 18.284,
    "distanceKm": 35,
    "lightPollution": 1,
    "horizon": "north",
    "description": "Quiet fjord area popular with aurora photographers."
  },
  {
    "id": "tromvik",
    "name": "Tromvik",
    "lat": 69.7766,
    "lon": 18.1322,
    "distanceKm": 50,
    "lightPollution": 1,
    "horizon": "north",
    "description": "Small fishing village with minimal light pollution."
  },
  {
    "id": "grunnfjord",
    "name": "Grunnfjord",
    "lat": 69.772,
    "lon": 18.198,
    "distanceKm": 45,
    "lightPollution": 1,
    "horizon": "north",
    "description": "Remote fjord location with little traffic or lighting."
  },
  {
    "id": "telegrafbukta",
    "name": "Telegrafbukta",
    "lat": 69.6311,
    "lon": 18.9317,
    "distanceKm": 3,
    "lightPollution": 2,
    "horizon": "north",
    "description": "Popular aurora viewing spot close to Tromsø city center.",
    "busStop": "Telegrafbukta, Sydspissen",
    "parking": "Folkeparken",
    "source": "Tromsø kommune"
  },
  {
    "id": "prestvannet",
    "name": "Prestvannet",
    "lat": 69.6533,
    "lon": 18.9339,
    "distanceKm": 2,
    "lightPollution": 2,
    "horizon": "north",
    "description": "Lake in Tromsø with darker skies than downtown.",
    "busStop": "Stalheim, Myreng",
    "parking": "Prestvannet, Samisk barnehage, Dyrebeskyttelsen",
    "source": "Tromsø kommune"
  },
  {
    "id": "fjellheisen_storsteinen",
    "name": "Fjellheisen / Storsteinen",
    "lat": 69.6408,
    "lon": 18.9873,
    "distanceKm": 2,
    "lightPollution": 2,
    "horizon": "north",
    "description": "Cable car viewpoint overlooking Tromsø with panoramic sky.",
    "busStop": "Fjellheisen",
    "parking": "Fjellheisen",
    "source": "Tromsø kommune"
  },
  {
    "id": "floya",
    "name": "Fløya",
    "lat": 69.6415,
    "lon": 18.995,
    "distanceKm": 3,
    "lightPollution": 2,
    "horizon": "north",
    "description": "Mountain above Tromsø with 360-degree sky visibility."
  },
  {
    "id": "vardentoppen",
    "name": "Vardentoppen",
    "lat": 69.665,
    "lon": 18.935,
    "distanceKm": 4,
    "lightPollution": 2,
    "horizon": "north",
    "description": "Hilltop viewpoint with wide night sky visibility."
  },
  {
    "id": "breivikeidet_valley",
    "name": "Breivikeidet Valley",
    "lat": 69.636,
    "lon": 19.616,
    "distanceKm": 45,
    "lightPollution": 1,
    "horizon": "northeast",
    "description": "Dark valley east of Tromsø often used by aurora tours.",
    "parking": "Breivikeidet",
    "source": "Tromsø kommune"
  },
  {
    "id": "oldervik",
    "name": "Oldervik",
    "lat": 69.7617,
    "lon": 19.5306,
    "distanceKm": 40,
    "lightPollution": 2,
    "horizon": "north",
    "description": "Quiet coastal village with good northern sky exposure."
  },
  {
    "id": "lyngseidet",
    "name": "Lyngseidet",
    "lat": 69.5763,
    "lon": 20.2186,
    "distanceKm": 75,
    "lightPollution": 1,
    "horizon": "north",
    "description": "Lyngen Alps region with dramatic mountain aurora views."
  },
  {
    "id": "skibotn",
    "name": "Skibotn",
    "lat": 69.3917,
    "lon": 20.2667,
    "distanceKm": 90,
    "lightPollution": 1,
    "horizon": "northeast",
    "description": "Dry inland valley known for clearer skies than the coast."
  },
  {
    "id": "signaldalen",
    "name": "Signaldalen",
    "lat": 69.3333,
    "lon": 20.2833,
    "distanceKm": 100,
    "lightPollution": 1,
    "horizon": "northeast",
    "description": "Dark inland valley often used as a cloud-escape aurora location."
  },
  {
    "id": "kilpisjarvi",
    "name": "Kilpisjärvi",
    "lat": 69.0444,
    "lon": 20.7992,
    "distanceKm": 160,
    "lightPollution": 1,
    "horizon": "north",
    "description": "High elevation Finnish Lapland aurora hotspot."
  },
  {
    "id": "nordjeteen",
    "name": "Nordjeteen",
    "lat": 69.6503,
    "lon": 18.9699,
    "distanceKm": 1,
    "lightPollution": 3,
    "horizon": "north",
    "description": "Waterfront viewpoint right in central Tromsø, an easy walk from downtown with bus access at Sentrum.",
    "busStop": "Sentrum",
    "source": "Tromsø kommune"
  },
  {
    "id": "skihytta",
    "name": "Skihytta",
    "lat": 69.6888,
    "lon": 18.9532,
    "distanceKm": 5,
    "lightPollution": 2,
    "horizon": "north",
    "description": "Ski lodge on the slopes above the city with less light spill than downtown, served by the Ekrehagen bus stop and parking.",
    "busStop": "Ekrehagen",
    "parking": "Ekrehagen",
    "source": "Tromsø kommune"
  },
  {
    "id": "nordspissen",
    "name": "Nordspissen",
    "lat": 69.7142,
    "lon": 19.0084,
    "distanceKm": 10,
    "lightPollution": 2,
    "horizon": "north",
    "description": "Northern tip of Tromsøya with an open view over the water, reachable via the Nesland bus stop with parking on site.",
    "busStop": "Nesland",
    "parking": "Nordspissen",
    "source": "Tromsø kommune"
  },
  {
    "id": "kattfjordeidet",
    "name": "Kattfjordeidet",
    "lat": 69.6649,
    "lon": 18.5811,
    "distanceKm": 15,
    "lightPollution": 1,
    "horizon": "north",
    "description": "Isthmus on Kvaløya between Kattfjorden and the open sea, with parking on site and dark skies away from the city.",
    "parking": "Kattfjordeidet",
    "source": "Tromsø kommune"
  },
  {
    "id": "vasstrand",
    "name": "Vasstrand",
    "lat": 69.6583,
    "lon": 18.2284,
    "distanceKm": 30,
    "lightPollution": 1,
    "horizon": "northwest",
    "description": "West-facing beach on outer Kvaløya with an open sea horizon and a marked parking area.",
    "parking": "Vasstrand",
    "source": "Tromsø kommune"
  },
  {
    "id": "rekvikvegen",
    "name": "Rekvikvegen",
    "lat": 69.7454,
    "lon": 18.3483,
    "distanceKm": 25,
    "lightPollution": 1,
    "horizon": "north",
    "description": "Quiet roadside pull-in on Kvaløya, parking available, with minimal surrounding light.",
    "parking": "Rekvikvegen",
    "source": "Tromsø kommune"
  },
  {
    "id": "grotfjord_litlevatnet",
    "name": "Grøtfjord – Litlevatnet (Kvaløya)",
    "lat": 69.7765,
    "lon": 18.564,
    "distanceKm": 20,
    "lightPollution": 1,
    "horizon": "north",
    "description": "Lakeside spot at Litlevatnet near Grøtfjord on Kvaløya, offering still-water reflections and a parking area.",
    "parking": "Grøtfjord - Litlevatnet",
    "source": "Tromsø kommune"
  },
  {
    "id": "tonsvika",
    "name": "Tønsvika",
    "lat": 69.7408,
    "lon": 19.1717,
    "distanceKm": 15,
    "lightPollution": 1,
    "horizon": "north",
    "description": "Coastal village east of Tromsø with parking available and darker skies than the city centre.",
    "parking": "Tønsvika",
    "source": "Tromsø kommune"
  },
  {
    "id": "finnvikdalen_sorskaret",
    "name": "Finnvikdalen - Sørskaret",
    "lat": 69.759,
    "lon": 18.8532,
    "distanceKm": 15,
    "lightPollution": 1,
    "horizon": "north",
    "description": "Valley pass on Kvaløya near Finnvik, across Sandnessundet from Tromsøya, well away from city lights, with a parking area.",
    "parking": "Finnvikdalen - Sørskaret",
    "source": "Tromsø kommune"
  }
]
